[
  {
    "id": "activity",
    "title": "Activity",
    "type": "query",
    "query": "involves:azu"
  },
  {
    "id": "inbox",
    "title": "Inbox",
    "type": "default",
    "items": [
      {
        "url": "https://github.com/facebook/react/issues/19670",
        "type": "issue"
      },
      {
        "url": "https://github.com/microsoft/TypeScript/issues/40124",
        "type": "issue"
      }
    ]
  },
  {
    "id": "progressing",
    "title": "Progressing",
    "type": "default",
    "items": [
    ]
  },
  {
    "id": "done",
    "title": "Done",
    "type": "default",
    "items": [
      {
        "url": "https://github.com/github/roadmap/issues/65",
        "type": "issue"
      },
      {
        "url": "https://github.com/github/opensource.guide/pull/1704",
        "type": "pull_request"
      }
    ]
  }
]
